simon/__init__.py
simon/locators.py
simon/pages.py
simon/accounts/__init__.py
simon/accounts/elements.py
simon/accounts/locators.py
simon/accounts/pages.py
simon/accounts/tests/__init__.py
simon/chat/__init__.py
simon/chat/elements.py
simon/chat/locators.py
simon/chat/pages.py
simon/chat/tests/__init__.py
simon/chats/__init__.py
simon/chats/elements.py
simon/chats/locators.py
simon/chats/pages.py
simon/chats/tests/__init__.py
simon/header/__init__.py
simon/header/elements.py
simon/header/locators.py
simon/header/pages.py
simon/header/tests/__init__.py
simon/search/__init__.py
"simon/search/elements,.py"
simon/search/locators.py
simon/search/pages.py
simon/search/tests/__init__.py
simon/tests/__init__.py
simon/tests/accounts.py
simon/tests/base.py
simon/tests/chat.py
simon/tests/chats.py
whatsapp_web-0.0.1.dist-info/LICENSE
whatsapp_web-0.0.1.dist-info/METADATA
whatsapp_web-0.0.1.dist-info/WHEEL
whatsapp_web-0.0.1.dist-info/top_level.txt
whatsapp_web-0.0.1.dist-info/RECORD
