Metadata-Version: 2.1
Name: whatsapp-web
Version: 0.0.1
Summary: A Python library to automate easily whatsapp web
Home-page: https://github.com/Fantaso/whatsapp-web
Author: fantaso
Author-email: fantaso.code@gmail.com
License: UNKNOWN
Platform: UNKNOWN
Classifier: Programming Language :: Python :: 3.8
Classifier: License :: OSI Approved :: MIT License
Classifier: Operating System :: OS Independent
Classifier: Development Status :: 4 - Beta
Classifier: Environment :: Web Environment :: Mozilla
Classifier: Natural Language :: English
Classifier: Topic :: Communications :: Chat
Requires-Python: >=3.6
